setuptools.autocythonize-0.3.2-py2.7-nspkg.pth
setuptools/autocythonize/__init__.py
setuptools.autocythonize-0.3.2.dist-info/DESCRIPTION.rst
setuptools.autocythonize-0.3.2.dist-info/entry_points.txt
setuptools.autocythonize-0.3.2.dist-info/METADATA
setuptools.autocythonize-0.3.2.dist-info/metadata.json
setuptools.autocythonize-0.3.2.dist-info/namespace_packages.txt
setuptools.autocythonize-0.3.2.dist-info/RECORD
setuptools.autocythonize-0.3.2.dist-info/top_level.txt
setuptools.autocythonize-0.3.2.dist-info/WHEEL
