Metadata-Version: 2.0
Name: setuptools.autocythonize
Version: 0.3.2
Summary: A setuptools util for generating an extensions list of cython modules, similar to find_packages, but also cythonizing the pyx files
Home-page: https://github.com/rocktavious/setuptools.autocythonize
Author: Kyle Rockman
Author-email: kyle.rockman@mac.com
License: UNKNOWN
Platform: UNKNOWN
